rps_client/__init__.py
rps_client/client.py
rps_client/config.py
rps_client/info.py
rps_client/logger.py
rps_client/models.py
rps_client/sdk.py
rps_client/utils.py
rps_client-1.0.1.dist-info/METADATA
rps_client-1.0.1.dist-info/WHEEL
rps_client-1.0.1.dist-info/RECORD
