Metadata-Version: 2.1
Name: rps-client
Version: 1.0.1
Summary: CUBETIQ RPS Client SDK for Python
License: MIT
Author: Sambo Chea
Author-email: sombochea@cubetiqs.com
Requires-Python: >=3.10,<4.0
Classifier: License :: OSI Approved :: MIT License
Classifier: Programming Language :: Python :: 3
Classifier: Programming Language :: Python :: 3.10
Classifier: Programming Language :: Python :: 3.11
